cruiseplan/__init__.py
cruiseplan/_version.py
cruiseplan/exceptions.py
cruiseplan/init_utils.py
cruiseplan/types.py
cruiseplan/api/__init__.py
cruiseplan/api/data.py
cruiseplan/api/map_cruise.py
cruiseplan/api/process_cruise.py
cruiseplan/api/schedule_cruise.py
cruiseplan/api/stations_api.py
cruiseplan/calculators/__init__.py
cruiseplan/calculators/distance.py
cruiseplan/calculators/duration.py
cruiseplan/calculators/routing.py
cruiseplan/calculators/scheduler.py
cruiseplan/cli/__init__.py
cruiseplan/cli/bathymetry.py
cruiseplan/cli/enrich.py
cruiseplan/cli/main.py
cruiseplan/cli/map.py
cruiseplan/cli/pangaea.py
cruiseplan/cli/process.py
cruiseplan/cli/schedule.py
cruiseplan/cli/stations.py
cruiseplan/cli/validate.py
cruiseplan/core/__init__.py
cruiseplan/core/cruise.py
cruiseplan/core/enrichment.py
cruiseplan/core/operations.py
cruiseplan/core/organizational.py
cruiseplan/core/serialization.py
cruiseplan/core/validation.py
cruiseplan/data/__init__.py
cruiseplan/data/bathymetry.py
cruiseplan/data/pangaea.py
cruiseplan/interactive/__init__.py
cruiseplan/interactive/campaign_selector.py
cruiseplan/interactive/station_picker.py
cruiseplan/interactive/widgets.py
cruiseplan/output/__init__.py
cruiseplan/output/csv_generator.py
cruiseplan/output/html_generator.py
cruiseplan/output/kml_generator.py
cruiseplan/output/latex_generator.py
cruiseplan/output/map_generator.py
cruiseplan/output/netcdf_generator.py
cruiseplan/output/netcdf_metadata.py
cruiseplan/output/output_utils.py
cruiseplan/output/templates/combined_tables.tex.j2
cruiseplan/output/templates/stations_table.tex.j2
cruiseplan/output/templates/work_days_table.tex.j2
cruiseplan/schema/__init__.py
cruiseplan/schema/activities.py
cruiseplan/schema/cruise_config.py
cruiseplan/schema/fields.py
cruiseplan/schema/ports.py
cruiseplan/schema/values.py
cruiseplan/schema/yaml_io.py
cruiseplan/utils/__init__.py
cruiseplan/utils/cache.py
cruiseplan/utils/coordinates.py
cruiseplan/utils/io.py
cruiseplan/utils/logging.py
cruiseplan-0.3.5.dist-info/licenses/LICENSE
cruiseplan-0.3.5.dist-info/METADATA
cruiseplan-0.3.5.dist-info/WHEEL
cruiseplan-0.3.5.dist-info/entry_points.txt
cruiseplan-0.3.5.dist-info/top_level.txt
cruiseplan-0.3.5.dist-info/RECORD
