Metadata-Version: 2.4
Name: cruiseplan
Version: 0.3.5
Summary: Oceanographic Research Cruise Planning System
Maintainer-email: Eleanor Frajka-Williams <eleanorfrajka@gmail.com>
License: MIT License
Project-URL: documentation, https://github.com/ocean-uhh/cruiseplan
Project-URL: homepage, https://github.com/ocean-uhh/cruiseplan
Project-URL: repository, https://github.com/ocean-uhh/cruiseplan
Classifier: Programming Language :: Python :: 3 :: Only
Classifier: Programming Language :: Python :: 3.9
Classifier: Programming Language :: Python :: 3.10
Classifier: Programming Language :: Python :: 3.11
Classifier: Programming Language :: Python :: 3.12
Classifier: Topic :: Scientific/Engineering :: GIS
Requires-Python: >=3.9
License-File: LICENSE
Requires-Dist: numpy>=1.21
Requires-Dist: pandas>=1.3.0
Requires-Dist: xarray>=2023.12.0
Requires-Dist: netCDF4>=1.5.8
Requires-Dist: scipy>=1.7.0
Requires-Dist: requests>=2.25.0
Requires-Dist: pangaeapy>=1.0.7
Requires-Dist: pydantic>=2.0.0
Requires-Dist: ruamel.yaml<0.20.0,>=0.17.0
Requires-Dist: matplotlib>=3.7
Requires-Dist: folium
Requires-Dist: branca
Requires-Dist: tqdm>=4.65
Requires-Dist: jinja2
Provides-Extra: dev
Requires-Dist: jupyterlab>=4.0; extra == "dev"
Requires-Dist: nbconvert>=7.8; extra == "dev"
Requires-Dist: myst-nb>=1.0; extra == "dev"
Requires-Dist: nbsphinx>=0.9; extra == "dev"
Requires-Dist: sphinx>=7.2; extra == "dev"
Requires-Dist: sphinx-rtd-theme>=2.0; extra == "dev"
Requires-Dist: pypandoc>=1.11; extra == "dev"
Requires-Dist: myst-parser>=2.0; extra == "dev"
Requires-Dist: pytest>=8.0; extra == "dev"
Requires-Dist: pytest-cov>=4.1; extra == "dev"
Requires-Dist: mock; extra == "dev"
Requires-Dist: pyyaml>=6.0; extra == "dev"
Requires-Dist: black>=24.0; extra == "dev"
Requires-Dist: ruff>=0.3; extra == "dev"
Requires-Dist: pre-commit>=3.5; extra == "dev"
Requires-Dist: codespell; extra == "dev"
Requires-Dist: mypy>=1.0; extra == "dev"
Requires-Dist: types-requests; extra == "dev"
Requires-Dist: types-tqdm; extra == "dev"
Requires-Dist: pandas-stubs; extra == "dev"
Dynamic: license-file
